foxtail_blog/__init__.py
foxtail_blog/admin.py
foxtail_blog/apps.py
foxtail_blog/feeds.py
foxtail_blog/forms.py
foxtail_blog/models.py
foxtail_blog/rules.py
foxtail_blog/settings.py
foxtail_blog/signals.py
foxtail_blog/sitemaps.py
foxtail_blog/urls.py
foxtail_blog/views.py
foxtail_blog/migrations/0001_initial.py
foxtail_blog/migrations/0002_pre-render_markdown.py
foxtail_blog/migrations/0003_optional_tags.py
foxtail_blog/migrations/0004_comments.py
foxtail_blog/migrations/0005_comment_length.py
foxtail_blog/migrations/0006_rendered_field.py
foxtail_blog/migrations/0007_django_published.py
foxtail_blog/migrations/0008_fix_ordering.py
foxtail_blog/migrations/0009_post_description.py
foxtail_blog/migrations/0010_rename_created.py
foxtail_blog/migrations/__init__.py
foxtail_blog/tests/__init__.py
foxtail_blog/tests/factories.py
foxtail_blog/tests/test_feed.py
foxtail_blog/tests/test_models.py
foxtail_blog/tests/test_urls.py
foxtail_blog-0.24.2.dist-info/LICENSE
foxtail_blog-0.24.2.dist-info/WHEEL
foxtail_blog-0.24.2.dist-info/METADATA
foxtail_blog-0.24.2.dist-info/RECORD
