Metadata-Version: 2.1
Name: foxtail-blog
Version: 0.24.2
Summary: A simple blog for Django 
Home-page: https://github.com/dmptrluke/foxtail-blog
Author: Luke Rogers
Author-email: luke@dmptr.com
Requires-Python: >=3.11
Classifier: Programming Language :: Python :: 3
Classifier: Programming Language :: Python :: 3.6
Classifier: Programming Language :: Python :: 3.7
Classifier: Programming Language :: Python :: 3.8
Classifier: Development Status :: 4 - Beta
Classifier: Framework :: Django
Classifier: Intended Audience :: Developers
Classifier: License :: OSI Approved :: MIT License
Classifier: Operating System :: OS Independent
Requires-Dist: django>=4
Requires-Dist: django-markdownfield>=0.6.1
Requires-Dist: django-taggit
Requires-Dist: django-versatileimagefield
Requires-Dist: django-crispy-forms
Requires-Dist: django-recaptcha
Requires-Dist: django-csp-helpers>=0.5.0
Requires-Dist: django-published>=0.7.0
Requires-Dist: rules
Requires-Dist: flit ; extra == "test"
Requires-Dist: atoma ; extra == "test"
Requires-Dist: coverage ; extra == "test"
Requires-Dist: factory-boy ; extra == "test"
Requires-Dist: django-environ ; extra == "test"
Requires-Dist: pytest ; extra == "test"
Requires-Dist: pytest-cov ; extra == "test"
Requires-Dist: pytest-django ; extra == "test"
Requires-Dist: pytest-factoryboy>=3.0.0 ; extra == "test"
Requires-Dist: pytest-xdist ; extra == "test"
Requires-Dist: selenium ; extra == "test"
Requires-Dist: tox ; extra == "test"
Provides-Extra: test
